pythonknot-0.1.16.dist-info/METADATA
pythonknot-0.1.16.dist-info/RECORD
pythonknot-0.1.16.dist-info/WHEEL
pythonknot-0.1.16.dist-info/top_level.txt
pythonknot.libs/libgmp-adce2ea4.so.10.4.0
pythonknot.libs/libgc-0cd783ac.so.1.3.2
pythonknot/__init__.py
pythonknot/rmsd.py
pythonknot/xyz.py
pythonknot/pdb_parser.cpython-311-x86_64-linux-gnu.so
pythonknot/homfly.cpython-311-x86_64-linux-gnu.so
pythonknot/knot_generator.py
pythonknot/alexander_poly.cpython-311-x86_64-linux-gnu.so
pythonknot/polymer.py
