Metadata-Version: 2.1
Name: pythonknot
Version: 0.1.16
Summary: pythonknot for knot theory calculation
Home-page: 
Author: yjianzhu
Author-email: yjianzhu@mail.ustc.edu.cn
Requires-Dist: numpy
Requires-Dist: scipy
Requires-Dist: pybind11[global]
Requires-Dist: rmsd
Requires-Dist: setuptools
Requires-Dist: wheel
